numberprym/numberPrym.py
numberprym-1.0.dist-info/LICENSE
numberprym-1.0.dist-info/METADATA
numberprym-1.0.dist-info/WHEEL
numberprym-1.0.dist-info/top_level.txt
numberprym-1.0.dist-info/RECORD
